{
  "source": "ruRU",
  "key": "ac4f0bad-92a0-40a2-9553-64e5a70b86b3",
  "ownerGuid": "e0926e74f6aa6a84a8441d999ef5c70a",
  "languages": [
    {
      "locale": "ruRU",
      "text": "На короткий период Осколок К'тан становится уязвимым ко всем атакам.",
      "modification_date": "2023-10-05T10:27:53.4101775+00:00",
      "translated_from": "enGB",
      "translation_date": "2023-10-05T10:27:53.4101778+00:00",
      "original_text": "For a short period, the C'tan Shard becomes {g|Encyclopedia:Vulnerable}vulnerable{/g} to all attacks.",
      "traits": [
        {
          "trait": "Translated",
          "trait_date": "2023-10-05T10:27:53.4101788+00:00",
          "locale_text": "На короткий период Осколок К'тан становится уязвимым ко всем атакам."
        },
        {
          "trait": "ASA_tr",
          "trait_date": "2023-10-05T10:27:53.4101791+00:00",
          "locale_text": "На короткий период Осколок К'тан становится уязвимым ко всем атакам."
        }
      ]
    },
    {
      "locale": "enGB",
      "text": "For a short period, the C'tan Shard becomes {g|Encyclopedia:Vulnerable}vulnerable{/g} to all attacks.",
      "modification_date": "2023-09-22T11:18:09.5097497+00:00",
      "translated_from": "ruRU",
      "translation_date": "2023-10-10T16:18:16.8490196+00:00",
      "original_text": "На короткий период Осколок К'тан становится уязвимым ко всем атакам.",
      "traits": [
        {
          "trait": "Edited",
          "trait_date": "2023-09-21T15:56:58.2660044+00:00",
          "locale_text": "For a short period, the C'tan Shard becomes vulnerable to all attacks."
        },
        {
          "trait": "JL_ed",
          "trait_date": "2024-07-29T10:04:51.0455989+00:00",
          "locale_text": "For a short period, the C'tan Shard becomes {g|Encyclopedia:Vulnerable}vulnerable{/g} to all attacks."
        }
      ]
    },
    {
      "locale": "esES",
      "text": "Durante un breve período, el fragmento de C'tan se vuelve {g|Encyclopedia:Vulnerable}vulnerable{/g} a todos los ataques.",
      "modification_date": "2023-09-29T08:19:49.5395491+00:00",
      "translated_from": "enGB",
      "translation_date": "2023-09-29T08:19:49.5395493+00:00",
      "original_text": "For a short period, the C'tan Shard becomes {g|Encyclopedia:Vulnerable}vulnerable{/g} to all attacks.",
      "traits": [
        {
          "trait": "Translated",
          "trait_date": "2023-09-29T08:19:49.5395504+00:00",
          "locale_text": "Durante un breve período, el fragmento de C'tan se vuelve {g|Encyclopedia:Vulnerable}vulnerable{/g} a todos los ataques."
        }
      ]
    },
    {
      "locale": "zhCN",
      "text": "在短时间内，星神碎片对所有攻击都处于{g|Encyclopedia:Vulnerable}易伤{/g}状态。",
      "modification_date": "2023-10-05T10:16:31.8232191+00:00",
      "translated_from": "enGB",
      "translation_date": "2023-10-17T14:12:28.2496674+00:00",
      "original_text": "For a short period, the C'tan Shard becomes {g|Encyclopedia:Vulnerable}vulnerable{/g} to all attacks.",
      "traits": [
        {
          "trait": "Translated",
          "trait_date": "2023-10-17T14:12:28.2496697+00:00",
          "locale_text": "在短时间内，星神碎片对所有攻击都处于{g|Encyclopedia:Vulnerable}易伤{/g}状态。"
        }
      ]
    },
    {
      "locale": "jaJP",
      "text": "しばらくの間、ク＝タン・シャードは全ての攻撃に対して{g|Encyclopedia:Vulnerable}脆弱化{/g}になる。",
      "modification_date": "2023-10-17T15:22:36.4444838+00:00",
      "translated_from": "enGB",
      "translation_date": "2023-11-09T10:06:54.8966531+00:00",
      "original_text": "For a short period, the C'tan Shard becomes {g|Encyclopedia:Vulnerable}vulnerable{/g} to all attacks.",
      "traits": [
        {
          "trait": "Translated",
          "trait_date": "2023-11-09T10:06:54.8966551+00:00",
          "locale_text": "しばらくの間、ク＝タン・シャードは全ての攻撃に対して{g|Encyclopedia:Vulnerable}脆弱化{/g}になる。"
        }
      ]
    },
    {
      "locale": "deDE",
      "text": "Für kurze Zeit wird das C'tan-Fragment für alle Angriffe {g|Encyclopedia:Vulnerable}verwundbar{/g}.",
      "modification_date": "2023-10-18T15:38:22.4046954+00:00",
      "translated_from": "enGB",
      "translation_date": "2023-10-18T19:11:16.3127632+00:00",
      "original_text": "For a short period, the C'tan Shard becomes {g|Encyclopedia:Vulnerable}vulnerable{/g} to all attacks.",
      "traits": [
        {
          "trait": "Translated",
          "trait_date": "2023-10-18T19:11:16.3127652+00:00",
          "locale_text": "Für kurze Zeit wird das C'tan-Fragment für alle Angriffe {g|Encyclopedia:Vulnerable}verwundbar{/g}."
        }
      ]
    },
    {
      "locale": "frFR",
      "text": "L'Écharde C'tan devient brièvement {g|Encyclopedia:Vulnerable}vulnérable{/g} à toutes les attaques.",
      "modification_date": "2023-10-18T15:56:31.8371334+00:00",
      "translated_from": "enGB",
      "translation_date": "2023-10-18T19:20:05.1963512+00:00",
      "original_text": "For a short period, the C'tan Shard becomes {g|Encyclopedia:Vulnerable}vulnerable{/g} to all attacks.",
      "traits": [
        {
          "trait": "Translated",
          "trait_date": "2023-10-18T19:20:05.1963518+00:00",
          "locale_text": "L'Écharde C'tan devient brièvement {g|Encyclopedia:Vulnerable}vulnérable{/g} à toutes les attaques."
        }
      ]
    }
  ],
  "string_traits": []
}