{
  "source": "ruRU",
  "key": "64b70854-f9ad-4560-99da-266a362099e5",
  "speaker": "TrueGvedon",
  "speakerGender": "Male",
  "ownerGuid": "d2112b2e196d4542a39f8b2ffa537a42",
  "languages": [
    {
      "locale": "ruRU",
      "text": "{n}Гведон роняет голову на грудь.{/n} \"Говорила ведь матушка, родился дураком — дураком и помру…\"",
      "modification_date": "2024-07-31T15:04:05.7069324+00:00",
      "traits": [
        {
          "trait": "CheckMe",
          "trait_date": "2024-07-31T15:04:05.7069324+00:00",
          "locale_text": "{n}Гведон роняет голову на грудь.{/n} \"Говорила ведь матушка, родился дураком — дураком и помру…\"",
          "speaker": "TrueGvedon",
          "speaker_gender": "Male"
        }
      ]
    },
    {
      "locale": "enGB",
      "text": "{n}Gwedon hangs his head.{/n} \"My mum always said I'd die an idiot...\"",
      "modification_date": "2024-08-10T00:50:35.8545044+00:00",
      "translated_from": "ruRU",
      "translation_date": "2024-09-05T08:16:04.5501364+00:00",
      "original_text": "{n}Гведон роняет голову на грудь.{/n} \"Говорила ведь матушка, родился дураком — дураком и помру…\"",
      "traits": [
        {
          "trait": "Translated",
          "trait_date": "2024-08-10T00:50:35.8545054+00:00",
          "locale_text": "{n}Gwedon hangs his head.{/n} \"My mum always said I'd die an idiot...\"",
          "speaker": "TrueGvedon",
          "speaker_gender": "Male"
        },
        {
          "trait": "TK_tr",
          "trait_date": "2024-08-10T00:50:35.8545058+00:00",
          "locale_text": "{n}Gwedon hangs his head.{/n} \"My mum always said I'd die an idiot...\"",
          "speaker": "TrueGvedon",
          "speaker_gender": "Male"
        },
        {
          "trait": "Edited",
          "trait_date": "2024-08-16T10:05:55.4260785+00:00",
          "locale_text": "{n}Gwedon hangs his head.{/n} \"My mum always said I'd die an idiot...\"",
          "speaker": "TrueGvedon",
          "speaker_gender": "Male"
        },
        {
          "trait": "FG_ed",
          "trait_date": "2024-08-16T10:05:55.4260787+00:00",
          "locale_text": "{n}Gwedon hangs his head.{/n} \"My mum always said I'd die an idiot...\"",
          "speaker": "TrueGvedon",
          "speaker_gender": "Male"
        },
        {
          "trait": "TK_rv",
          "trait_date": "2024-09-05T08:16:04.5501385+00:00",
          "locale_text": "{n}Gwedon hangs his head.{/n} \"My mum always said I'd die an idiot...\"",
          "speaker": "TrueGvedon",
          "speaker_gender": "Male"
        },
        {
          "trait": "Reviewed",
          "trait_date": "2024-09-05T08:16:04.5501388+00:00",
          "locale_text": "{n}Gwedon hangs his head.{/n} \"My mum always said I'd die an idiot...\"",
          "speaker": "TrueGvedon",
          "speaker_gender": "Male"
        },
        {
          "trait": "Turkish",
          "trait_date": "2024-09-16T12:12:16.727421+00:00",
          "locale_text": "{n}Gwedon hangs his head.{/n} \"My mum always said I'd die an idiot...\"",
          "speaker": "TrueGvedon",
          "speaker_gender": "Male"
        }
      ]
    },
    {
      "locale": "frFR",
      "text": "{n}Gwedon baisse la tête.{/n} « Ma mère disait toujours que je mourrais aussi niais qu'au jour de ma naissance... »",
      "modification_date": "2024-09-19T11:31:08.7756876+00:00",
      "translated_from": "enGB",
      "translation_date": "2024-09-19T11:31:08.7756878+00:00",
      "original_text": "{n}Gwedon hangs his head.{/n} \"My mum always said I'd die an idiot...\"",
      "traits": [
        {
          "trait": "Translated",
          "trait_date": "2024-09-19T11:31:08.7756904+00:00",
          "locale_text": "{n}Gwedon baisse la tête.{/n} « Ma mère disait toujours que je mourrais aussi niais qu'au jour de ma naissance... »",
          "speaker": "TrueGvedon",
          "speaker_gender": "Male"
        }
      ]
    },
    {
      "locale": "esES",
      "text": "{n}Gwedon baja la cabeza.{/n} «Mi madre siempre decía que moriría siendo un idiota...».",
      "modification_date": "2024-09-25T11:28:47.934344+00:00",
      "translated_from": "enGB",
      "translation_date": "2024-09-25T11:28:47.9343444+00:00",
      "original_text": "{n}Gwedon hangs his head.{/n} \"My mum always said I'd die an idiot...\"",
      "traits": [
        {
          "trait": "Translated",
          "trait_date": "2024-09-25T11:28:47.9343476+00:00",
          "locale_text": "{n}Gwedon baja la cabeza.{/n} «Mi madre siempre decía que moriría siendo un idiota...».",
          "speaker": "TrueGvedon",
          "speaker_gender": "Male"
        }
      ]
    },
    {
      "locale": "jaJP",
      "text": "{n}グウェドンは頭を傾けた。{/n}「私の母親はいつも、私がアホとして死んでいくと言っていました…」",
      "modification_date": "2024-09-25T11:28:48.066859+00:00",
      "translated_from": "enGB",
      "translation_date": "2024-09-25T11:28:48.0668597+00:00",
      "original_text": "{n}Gwedon hangs his head.{/n} \"My mum always said I'd die an idiot...\"",
      "traits": [
        {
          "trait": "Translated",
          "trait_date": "2024-09-25T11:28:48.0668626+00:00",
          "locale_text": "{n}グウェドンは頭を傾けた。{/n}「私の母親はいつも、私がアホとして死んでいくと言っていました…」",
          "speaker": "TrueGvedon",
          "speaker_gender": "Male"
        }
      ]
    },
    {
      "locale": "zhCN",
      "text": "{n}戈登垂下了头。{/n}“我妈以前总说，我到死都是个白痴……”",
      "modification_date": "2024-09-25T11:28:48.2322922+00:00",
      "translated_from": "enGB",
      "translation_date": "2024-09-25T11:28:48.232293+00:00",
      "original_text": "{n}Gwedon hangs his head.{/n} \"My mum always said I'd die an idiot...\"",
      "traits": [
        {
          "trait": "Translated",
          "trait_date": "2024-09-25T11:28:48.2322998+00:00",
          "locale_text": "{n}戈登垂下了头。{/n}“我妈以前总说，我到死都是个白痴……”",
          "speaker": "TrueGvedon",
          "speaker_gender": "Male"
        }
      ]
    },
    {
      "locale": "deDE",
      "text": "{n}Gwedon lässt den Kopf hängen.{/n} \"Meine Mutter hat immer gesagt, ich würde dumm sterben ...\"",
      "modification_date": "2024-09-27T13:04:34.8221658+00:00",
      "translated_from": "enGB",
      "translation_date": "2024-09-27T13:04:34.822166+00:00",
      "original_text": "{n}Gwedon hangs his head.{/n} \"My mum always said I'd die an idiot...\"",
      "traits": [
        {
          "trait": "Translated",
          "trait_date": "2024-09-27T13:04:34.8221665+00:00",
          "locale_text": "{n}Gwedon lässt den Kopf hängen.{/n} \"Meine Mutter hat immer gesagt, ich würde dumm sterben ...\"",
          "speaker": "TrueGvedon",
          "speaker_gender": "Male"
        }
      ]
    }
  ],
  "string_traits": [
    {
      "trait": "DLC1",
      "trait_date": "2024-08-08T09:48:19.9939411+00:00",
      "locale_text": "",
      "speaker": "TrueGvedon",
      "speaker_gender": "Male"
    },
    {
      "trait": "To_translate",
      "trait_date": "2024-08-08T09:48:19.9939415+00:00",
      "locale_text": "",
      "speaker": "TrueGvedon",
      "speaker_gender": "Male"
    },
    {
      "trait": "DLC_after_26.06",
      "trait_date": "2024-08-08T09:48:19.9939416+00:00",
      "locale_text": "",
      "speaker": "TrueGvedon",
      "speaker_gender": "Male"
    },
    {
      "trait": "WH-300253",
      "trait_date": "2024-08-08T09:48:19.9939417+00:00",
      "locale_text": "",
      "speaker": "TrueGvedon",
      "speaker_gender": "Male"
    },
    {
      "trait": "пак_на_редактуру",
      "trait_date": "2024-08-13T08:31:36.3398571+00:00",
      "locale_text": "",
      "speaker": "TrueGvedon",
      "speaker_gender": "Male"
    },
    {
      "trait": "пак_ревью",
      "trait_date": "2024-08-26T07:48:24.2351945+00:00",
      "locale_text": "",
      "speaker": "TrueGvedon",
      "speaker_gender": "Male"
    },
    {
      "trait": "DLC_DoNotTranslate_Alexey",
      "trait_date": "2024-09-01T11:11:57.7641597+00:00",
      "locale_text": "",
      "speaker": "TrueGvedon",
      "speaker_gender": "Male"
    },
    {
      "trait": "DLC1_Patch",
      "trait_date": "2024-09-09T12:29:20.1272758+00:00",
      "locale_text": "",
      "speaker": "TrueGvedon",
      "speaker_gender": "Male"
    },
    {
      "trait": "DLC_Sent_OtherLocs",
      "trait_date": "2024-09-10T08:57:43.9855587+00:00",
      "locale_text": "",
      "speaker": "TrueGvedon",
      "speaker_gender": "Male"
    },
    {
      "trait": "Batch14",
      "trait_date": "2024-09-10T08:57:43.9855593+00:00",
      "locale_text": "",
      "speaker": "TrueGvedon",
      "speaker_gender": "Male"
    }
  ]
}