{
  "source": "enGB",
  "key": "9a626cd5-1ea4-412b-9f41-ff46cba0b1d5",
  "ownerGuid": "1df2e025c0a57a14fac6017cd46a3b61",
  "languages": [
    {
      "locale": "enGB",
      "text": "Followers of the Cult of Saint Drusus, a legendary hero of the Angevin Crusade.",
      "modification_date": "2023-09-25T18:11:29.9089101+00:00",
      "translated_from": "ruRU",
      "translation_date": "2023-10-04T16:08:12.1296717+00:00",
      "original_text": "Последователи культа святого Друза, легендарного героя Анжуйского крестового похода",
      "traits": [
        {
          "trait": "Edited",
          "trait_date": "2023-09-25T18:11:29.9089116+00:00",
          "locale_text": "Followers of the Cult of Saint Drusus, a legendary hero of the Angevin Crusade."
        },
        {
          "trait": "JL_ed",
          "trait_date": "2023-09-25T18:11:29.9089118+00:00",
          "locale_text": "Followers of the Cult of Saint Drusus, a legendary hero of the Angevin Crusade."
        },
        {
          "trait": "Turkish",
          "trait_date": "2024-07-16T08:42:35.5180512+00:00",
          "locale_text": "Followers of the Cult of Saint Drusus, a legendary hero of the Angevin Crusade."
        }
      ]
    },
    {
      "locale": "deDE",
      "text": "Anhänger des Kultes des Heiligen Drusus, eines legendären Helden des Anjou-Kreuzzugs.",
      "modification_date": "2023-10-18T15:42:52.6053652+00:00",
      "translated_from": "enGB",
      "translation_date": "2024-11-26T09:42:01.0702824+00:00",
      "original_text": "Followers of the Cult of Saint Drusus, a legendary hero of the Angevin Crusade.",
      "traits": [
        {
          "trait": "Translated",
          "trait_date": "2023-10-18T19:11:37.9381698+00:00",
          "locale_text": "Anhänger des Kultes des Heiligen Drusus, eines legendären Helden des Anjou-Kreuzzugs."
        }
      ]
    },
    {
      "locale": "frFR",
      "text": "Serviteurs du culte de Saint Drusus, légendaire héros de la Croisade d'Angevin.",
      "modification_date": "2023-10-18T15:56:57.3258692+00:00",
      "translated_from": "enGB",
      "translation_date": "2024-11-26T07:18:58.3865669+00:00",
      "original_text": "Followers of the Cult of Saint Drusus, a legendary hero of the Angevin Crusade.",
      "traits": [
        {
          "trait": "Translated",
          "trait_date": "2023-10-18T15:56:57.3258718+00:00",
          "locale_text": "Serviteurs du culte de Saint Drusus, légendaire héros de la Croisade d'Angevin."
        }
      ]
    },
    {
      "locale": "zhCN",
      "text": "圣德鲁苏斯教派的追随者，圣德鲁苏斯是安杰文远征期间的传奇英雄。",
      "modification_date": "2023-10-09T14:24:58.0585767+00:00",
      "translated_from": "enGB",
      "translation_date": "2023-10-17T14:12:23.1271973+00:00",
      "original_text": "Followers of the Cult of Saint Drusus, a legendary hero of the Angevin Crusade.",
      "traits": [
        {
          "trait": "Translated",
          "trait_date": "2023-10-17T14:12:23.1271988+00:00",
          "locale_text": "圣德鲁苏斯教派的追随者，圣德鲁苏斯是安杰文远征期间的传奇英雄。"
        }
      ]
    },
    {
      "locale": "esES",
      "text": "Seguidores del Culto de San Drusus, héroe legendario de la Cruzada de Angevin.",
      "modification_date": "2023-10-18T14:29:56.4627851+00:00",
      "translated_from": "enGB",
      "translation_date": "2023-10-18T14:29:56.4627861+00:00",
      "original_text": "Followers of the Cult of Saint Drusus, a legendary hero of the Angevin Crusade.",
      "traits": [
        {
          "trait": "Translated",
          "trait_date": "2023-10-18T14:29:56.4627874+00:00",
          "locale_text": "Seguidores del Culto de San Drusus, héroe legendario de la Cruzada de Angevin."
        }
      ]
    },
    {
      "locale": "jaJP",
      "text": "アンジュー十字軍の伝説的英雄である聖ドルスス教団の信徒。",
      "modification_date": "2023-11-09T10:06:50.2167653+00:00",
      "translated_from": "enGB",
      "translation_date": "2023-11-09T10:06:50.2167658+00:00",
      "original_text": "Followers of the Cult of Saint Drusus, a legendary hero of the Angevin Crusade.",
      "traits": [
        {
          "trait": "Translated",
          "trait_date": "2023-11-09T10:06:50.2167676+00:00",
          "locale_text": "アンジュー十字軍の伝説的英雄である聖ドルスス教団の信徒。"
        }
      ]
    },
    {
      "locale": "ruRU",
      "text": "Последователи культа святого Друза, легендарного героя Анжуйского крестового похода",
      "modification_date": "2023-09-05T19:08:10.4649822+00:00",
      "translated_from": "enGB",
      "translation_date": "2023-09-05T19:08:10.4649827+00:00",
      "original_text": "Followers of the Cult of Saint Drusus, a legendary hero of the Angevin Crusade",
      "traits": []
    }
  ],
  "string_traits": [
    {
      "trait": "OtherLocs_ToReview",
      "trait_date": "2023-10-03T20:01:09.4083447+00:00",
      "locale_text": ""
    }
  ]
}