{
  "source": "ruRU",
  "key": "7cb3cf8b-189b-4f34-9251-f2031fef2a42",
  "speaker": "KibellahCompanion",
  "speakerGender": "Female",
  "ownerGuid": "0d840fb28da344c685c27c8ce702447e",
  "languages": [
    {
      "locale": "ruRU",
      "text": "{n}Напряженность в голосе тает, сменяясь теплом доверия.{/n} \"И каков же будет твой следующий шаг, Домин'{name}?\"",
      "modification_date": "2024-06-30T09:23:42.2465813Z",
      "traits": []
    },
    {
      "locale": "enGB",
      "text": "{n}The tension in her voice fades, giving way to warmth and trust.{/n} \"So, then... what will your next step be, Domin'{name}?\"",
      "modification_date": "2024-07-08T09:27:01.025265Z",
      "translated_from": "ruRU",
      "translation_date": "2024-07-09T22:32:46.9211627+00:00",
      "original_text": "{n}Напряженность в голосе тает, сменяясь теплом доверия.{/n} \"И каков же будет твой следующий шаг, Домин'{name}?\"",
      "traits": [
        {
          "trait": "Translated",
          "trait_date": "2024-07-02T23:34:56.6769709Z",
          "locale_text": "{n}The tension in her voice fades, giving way to warmth and trust.{/n} \"So, then... What will your next step be, Domin'{name}?\"",
          "speaker": "",
          "speaker_gender": ""
        },
        {
          "trait": "TK_tr",
          "trait_date": "2024-07-02T23:34:56.6769713Z",
          "locale_text": "{n}The tension in her voice fades, giving way to warmth and trust.{/n} \"So, then... What will your next step be, Domin'{name}?\"",
          "speaker": "",
          "speaker_gender": ""
        },
        {
          "trait": "Edited",
          "trait_date": "2024-07-08T09:27:01.0252666Z",
          "locale_text": "{n}The tension in her voice fades, giving way to warmth and trust.{/n} \"So, then... what will your next step be, Domin'{name}?\"",
          "speaker": "",
          "speaker_gender": ""
        },
        {
          "trait": "FG_ed",
          "trait_date": "2024-07-08T09:27:01.025267Z",
          "locale_text": "{n}The tension in her voice fades, giving way to warmth and trust.{/n} \"So, then... what will your next step be, Domin'{name}?\"",
          "speaker": "",
          "speaker_gender": ""
        },
        {
          "trait": "TK_rv",
          "trait_date": "2024-07-09T22:32:46.9211659Z",
          "locale_text": "{n}The tension in her voice fades, giving way to warmth and trust.{/n} \"So, then... what will your next step be, Domin'{name}?\"",
          "speaker": "",
          "speaker_gender": ""
        },
        {
          "trait": "Turkish",
          "trait_date": "2024-09-16T12:12:08.0423773Z",
          "locale_text": "{n}The tension in her voice fades, giving way to warmth and trust.{/n} \"So, then... what will your next step be, Domin'{name}?\"",
          "speaker": "",
          "speaker_gender": ""
        }
      ]
    },
    {
      "locale": "esES",
      "text": "{n}La tensión de su voz desaparece, dando paso a la calidez y la confianza.{/n} «En ese caso... ¿cuál será su próximo paso, Domin'{name}?».",
      "modification_date": "2024-08-27T14:48:30.0374957Z",
      "translated_from": "enGB",
      "translation_date": "2024-08-27T14:48:30.0374959+00:00",
      "original_text": "{n}The tension in her voice fades, giving way to warmth and trust.{/n} \"So, then... what will your next step be, Domin'{name}?\"",
      "traits": [
        {
          "trait": "Translated",
          "trait_date": "2024-08-27T14:48:30.0374978Z",
          "locale_text": "{n}La tensión de su voz desaparece, dando paso a la calidez y la confianza.{/n} «En ese caso... ¿cuál será su próximo paso, Domin'{name}?».",
          "speaker": "",
          "speaker_gender": ""
        }
      ]
    },
    {
      "locale": "jaJP",
      "text": "{n}緊張が彼女の声から消え去り、暖かい信頼できるトーンになった。{/n}「では…次はどうするんですか、ドミン{name}？」",
      "modification_date": "2024-08-27T14:49:29.628888Z",
      "translated_from": "enGB",
      "translation_date": "2024-08-27T14:49:29.6288882+00:00",
      "original_text": "{n}The tension in her voice fades, giving way to warmth and trust.{/n} \"So, then... what will your next step be, Domin'{name}?\"",
      "traits": [
        {
          "trait": "Translated",
          "trait_date": "2024-08-27T14:49:29.6288888Z",
          "locale_text": "{n}緊張が彼女の声から消え去り、暖かい信頼できるトーンになった。{/n}「では…次はどうするんですか、ドミン{name}？」",
          "speaker": "",
          "speaker_gender": ""
        }
      ]
    },
    {
      "locale": "zhCN",
      "text": "{n}她声音中的紧张之意消失了，取而代之的是温暖与信任。{/n}“既然如此……你接下来打算怎么办呢，秘者{name}？”",
      "modification_date": "2024-08-27T14:50:29.7420374Z",
      "translated_from": "enGB",
      "translation_date": "2024-08-27T14:50:29.7420376+00:00",
      "original_text": "{n}The tension in her voice fades, giving way to warmth and trust.{/n} \"So, then... what will your next step be, Domin'{name}?\"",
      "traits": [
        {
          "trait": "Translated",
          "trait_date": "2024-08-27T14:50:29.742038Z",
          "locale_text": "{n}她声音中的紧张之意消失了，取而代之的是温暖与信任。{/n}“既然如此……你接下来打算怎么办呢，秘者{name}？”",
          "speaker": "",
          "speaker_gender": ""
        }
      ]
    },
    {
      "locale": "deDE",
      "text": "{n}Die Anspannung in ihrer Stimme schwindet und wird ersetzt durch Wärme und Vertrauen.{/n} \"Nun ... was wird Euer nächster Schritt sein, Domin'{name}?\"",
      "modification_date": "2024-09-10T10:27:18.0848457Z",
      "translated_from": "enGB",
      "translation_date": "2024-09-10T10:27:18.0848459+00:00",
      "original_text": "{n}The tension in her voice fades, giving way to warmth and trust.{/n} \"So, then... what will your next step be, Domin'{name}?\"",
      "traits": [
        {
          "trait": "Translated",
          "trait_date": "2024-09-10T10:27:18.0848478Z",
          "locale_text": "{n}Die Anspannung in ihrer Stimme schwindet und wird ersetzt durch Wärme und Vertrauen.{/n} \"Nun ... was wird Euer nächster Schritt sein, Domin'{name}?\"",
          "speaker": "",
          "speaker_gender": ""
        }
      ]
    },
    {
      "locale": "frFR",
      "text": "{n}La tension dans sa voix s'estompe, cédant la place à une confiance débonnaire.{/n} « Et donc... que comptez-vous faire à ce sujet, Domin'{name} ? »",
      "modification_date": "2024-09-11T09:52:21.0264397Z",
      "translated_from": "enGB",
      "translation_date": "2024-09-11T09:52:21.02644+00:00",
      "original_text": "{n}The tension in her voice fades, giving way to warmth and trust.{/n} \"So, then... what will your next step be, Domin'{name}?\"",
      "traits": [
        {
          "trait": "Translated",
          "trait_date": "2024-09-11T09:52:21.0264418Z",
          "locale_text": "{n}La tension dans sa voix s'estompe, cédant la place à une confiance débonnaire.{/n} « Et donc... que comptez-vous faire à ce sujet, Domin'{name} ? »",
          "speaker": "",
          "speaker_gender": ""
        }
      ]
    }
  ],
  "string_traits": [
    {
      "trait": "DLC1",
      "trait_date": "2024-07-01T15:46:09.3948463Z",
      "locale_text": "",
      "speaker": "",
      "speaker_gender": ""
    },
    {
      "trait": "DCL1_after_26.06",
      "trait_date": "2024-07-01T15:46:09.3948466Z",
      "locale_text": "",
      "speaker": "",
      "speaker_gender": ""
    },
    {
      "trait": "WH-284438",
      "trait_date": "2024-07-01T13:28:57.3335431Z",
      "locale_text": "",
      "speaker": "",
      "speaker_gender": ""
    },
    {
      "trait": "DLC_Sent_OtherLocs",
      "trait_date": "2024-07-26T12:49:17.8591461Z",
      "locale_text": "",
      "speaker": "",
      "speaker_gender": ""
    },
    {
      "trait": "Batch9",
      "trait_date": "2024-07-26T12:49:17.8591467Z",
      "locale_text": "",
      "speaker": "",
      "speaker_gender": ""
    },
    {
      "trait": "Будут_правки_ГВ",
      "trait_date": "2024-08-29T09:10:00.7406849Z",
      "locale_text": "",
      "speaker": "",
      "speaker_gender": ""
    }
  ]
}