{
  "source": "enGB",
  "key": "499f4216-e6a2-4a3d-9b3f-8873080dade4",
  "ownerGuid": "10aae738ddd3e7d4cbf197509a31f221",
  "languages": [
    {
      "locale": "enGB",
      "text": "Disciple's Boots",
      "modification_date": "2022-10-21T06:44:23.3329652Z",
      "traits": [
        {
          "trait": "Texts_Alisa",
          "trait_date": "2023-09-20T21:53:03.842412Z",
          "locale_text": "Disciple's Boots"
        },
        {
          "trait": "Edited",
          "trait_date": "2023-10-03T13:51:25.9752354Z",
          "locale_text": "Disciple's Boots"
        },
        {
          "trait": "JL_ed",
          "trait_date": "2023-10-03T13:51:25.9752356Z",
          "locale_text": "Disciple's Boots"
        }
      ]
    },
    {
      "locale": "zhCN",
      "text": "门徒之靴",
      "modification_date": "2023-10-09T14:24:56.6422579Z",
      "translated_from": "enGB",
      "translation_date": "2023-10-17T14:12:21.4928416+00:00",
      "original_text": "Disciple's Boots",
      "traits": [
        {
          "trait": "Translated",
          "trait_date": "2023-10-17T14:12:21.4928434Z",
          "locale_text": "门徒之靴"
        }
      ]
    },
    {
      "locale": "jaJP",
      "text": "弟子用ブーツ",
      "modification_date": "2023-10-13T08:38:14.7823245Z",
      "translated_from": "enGB",
      "translation_date": "2023-11-09T10:06:48.6466463+00:00",
      "original_text": "Disciple's Boots",
      "traits": [
        {
          "trait": "Translated",
          "trait_date": "2023-11-09T10:06:48.6466492Z",
          "locale_text": "弟子用ブーツ"
        }
      ]
    },
    {
      "locale": "esES",
      "text": "Botas de discípulo",
      "modification_date": "2023-10-18T14:29:54.2529642Z",
      "translated_from": "enGB",
      "translation_date": "2023-10-18T14:29:54.2529644+00:00",
      "original_text": "Disciple's Boots",
      "traits": [
        {
          "trait": "Translated",
          "trait_date": "2023-10-18T14:29:54.2529659Z",
          "locale_text": "Botas de discípulo"
        }
      ]
    },
    {
      "locale": "deDE",
      "text": "Jüngerstiefel",
      "modification_date": "2023-10-18T15:42:50.7682296Z",
      "translated_from": "enGB",
      "translation_date": "2023-10-18T19:11:36.2741689+00:00",
      "original_text": "Disciple's Boots",
      "traits": [
        {
          "trait": "Translated",
          "trait_date": "2023-10-18T19:11:36.2741701Z",
          "locale_text": "Jüngerstiefel"
        }
      ]
    },
    {
      "locale": "ruRU",
      "text": "Сапоги приверженца",
      "modification_date": "2023-10-18T15:48:34.6263263Z",
      "translated_from": "enGB",
      "translation_date": "2023-10-18T15:50:59.8291564+00:00",
      "original_text": "Disciple's Boots",
      "traits": [
        {
          "trait": "Translated",
          "trait_date": "2023-10-18T15:50:59.8291571Z",
          "locale_text": "Сапоги приверженца"
        },
        {
          "trait": "ASA_tr",
          "trait_date": "2023-10-18T15:50:59.8291574Z",
          "locale_text": "Сапоги приверженца"
        }
      ]
    },
    {
      "locale": "frFR",
      "text": "Bottes du Disciple",
      "modification_date": "2023-10-18T15:56:56.9686936Z",
      "translated_from": "enGB",
      "translation_date": "2023-10-18T19:37:21.1329896+00:00",
      "original_text": "Disciple's Boots",
      "traits": [
        {
          "trait": "Translated",
          "trait_date": "2023-10-18T19:37:21.1329905Z",
          "locale_text": "Bottes du Disciple"
        }
      ]
    }
  ],
  "string_traits": [
    {
      "trait": "OtherLocs_ToReview",
      "trait_date": "2023-10-03T19:48:42.1544359Z",
      "locale_text": ""
    }
  ]
}