{
  "source": "ruRU",
  "key": "7130735a-369e-4389-b274-0c34179fb925",
  "speaker": "FootfallVendorServitor",
  "speakerGender": "Male",
  "ownerGuid": "567e8d59a68a47ba9be2c3a4afbb18b1",
  "languages": [
    {
      "locale": "ruRU",
      "text": "\"Проигрываю автоматическое уведомление, внемлите. Флот Осознание одобряет ваше стремление внести вклад в дело всепознания. Флот Осознание готов принимать дальнейшие инфопожертвования\".",
      "modification_date": "2023-04-26T15:33:45.2278507+00:00",
      "translation_comment": "",
      "traits": [
        {
          "trait": "CheckMe",
          "trait_date": "2023-04-26T15:33:45.2278507+00:00",
          "locale_text": "\"Проигрываю автоматическое уведомление, внемлите. Флот Осознание одобряет ваше стремление внести вклад в дело всепознания. Флот Осознание готов принимать дальнейшие инфопожертвования\"."
        }
      ]
    },
    {
      "locale": "enGB",
      "text": "\"Replaying automatic notification. Hear and heed. The Cognisance Fleet approves of your wish to contribute to the cause of total knowledge acquisition. The Cognisance Fleet is open to further data donations.\"",
      "modification_date": "2023-07-31T18:06:30.1064795+03:00",
      "translation_comment": "",
      "translated_from": "ruRU",
      "translation_date": "2024-03-25T10:02:31.8374169+00:00",
      "original_text": "\"Проигрываю автоматическое уведомление, внемлите. Флот Осознание одобряет ваше стремление внести вклад в дело всепознания. Флот Осознание готов принимать дальнейшие инфопожертвования\".",
      "traits": [
        {
          "trait": "Translated",
          "trait_date": "2023-07-31T18:06:30.1064814+03:00",
          "locale_text": "\"Replaying automatic notification. Hear and heed. The Cognisance Fleet approves of your wish to contribute to the cause of total knowledge acquisition. The Cognisance Fleet is open to further data donations.\""
        },
        {
          "trait": "NE_tr",
          "trait_date": "2023-07-31T18:06:30.1064821+03:00",
          "locale_text": "\"Replaying automatic notification. Hear and heed. The Cognisance Fleet approves of your wish to contribute to the cause of total knowledge acquisition. The Cognisance Fleet is open to further data donations.\""
        },
        {
          "trait": "Edited",
          "trait_date": "2023-08-28T13:29:53.3852414+00:00",
          "locale_text": "\"Replaying automatic notification. Hear and heed. The Cognisance Fleet approves of your wish to contribute to the cause of total knowledge acquisition. The Cognisance Fleet is open to further data donations.\""
        },
        {
          "trait": "LG_ed",
          "trait_date": "2023-08-28T13:29:53.3852421+00:00",
          "locale_text": "\"Replaying automatic notification. Hear and heed. The Cognisance Fleet approves of your wish to contribute to the cause of total knowledge acquisition. The Cognisance Fleet is open to further data donations.\""
        },
        {
          "trait": "AD_rv",
          "trait_date": "2024-03-25T10:02:31.8374203+00:00",
          "locale_text": "\"Replaying automatic notification. Hear and heed. The Cognisance Fleet approves of your wish to contribute to the cause of total knowledge acquisition. The Cognisance Fleet is open to further data donations.\""
        },
        {
          "trait": "Turkish",
          "trait_date": "2024-03-25T13:49:22.8509079+00:00",
          "locale_text": "\"Replaying automatic notification. Hear and heed. The Cognisance Fleet approves of your wish to contribute to the cause of total knowledge acquisition. The Cognisance Fleet is open to further data donations.\""
        }
      ]
    },
    {
      "locale": "zhCN",
      "text": "“正在重复自动通知。请听好，真理开拓者舰队认可您对求知事业做出的光荣贡献。真理开拓者舰队欢迎进一步的数据捐赠。”",
      "modification_date": "2023-09-28T14:28:33.2424621+00:00",
      "translation_comment": "",
      "translated_from": "enGB",
      "translation_date": "2023-09-28T14:28:33.2424623+00:00",
      "original_text": "\"Replaying automatic notification. Hear and heed. The Cognisance Fleet approves of your wish to contribute to the cause of total knowledge acquisition. The Cognisance Fleet is open to further data donations.\"",
      "traits": [
        {
          "trait": "Translated",
          "trait_date": "2023-09-28T14:28:33.242464+00:00",
          "locale_text": "“正在重复自动通知。请听好，真理开拓者舰队认可您对求知事业做出的光荣贡献。真理开拓者舰队欢迎进一步的数据捐赠。”"
        }
      ]
    },
    {
      "locale": "jaJP",
      "text": "「自動通知を再生中。お聞きください。コグニサンス艦隊は完全な知識獲得の大義に貢献したいというあなたの希望を承認します。コグニサンス艦隊は、データの寄付を受け付けています」",
      "modification_date": "2023-09-28T14:29:30.5035211+00:00",
      "translation_comment": "",
      "translated_from": "enGB",
      "translation_date": "2023-09-28T14:29:30.5035213+00:00",
      "original_text": "\"Replaying automatic notification. Hear and heed. The Cognisance Fleet approves of your wish to contribute to the cause of total knowledge acquisition. The Cognisance Fleet is open to further data donations.\"",
      "traits": [
        {
          "trait": "Translated",
          "trait_date": "2023-09-28T14:29:30.503522+00:00",
          "locale_text": "「自動通知を再生中。お聞きください。コグニサンス艦隊は完全な知識獲得の大義に貢献したいというあなたの希望を承認します。コグニサンス艦隊は、データの寄付を受け付けています」"
        }
      ]
    },
    {
      "locale": "esES",
      "text": "«Repetición de notificación automática. Escuche y preste atención. La Flota Conciencia aprueba su deseo de contribuir a la causa de la adquisición total de conocimiento. La Flota Conciencia está abierta a más donaciones de datos».",
      "modification_date": "2023-10-09T12:55:34.8174161+00:00",
      "translation_comment": "",
      "translated_from": "enGB",
      "translation_date": "2023-10-09T12:55:34.8174163+00:00",
      "original_text": "\"Replaying automatic notification. Hear and heed. The Cognisance Fleet approves of your wish to contribute to the cause of total knowledge acquisition. The Cognisance Fleet is open to further data donations.\"",
      "traits": [
        {
          "trait": "Translated",
          "trait_date": "2023-10-09T12:55:34.8174168+00:00",
          "locale_text": "«Repetición de notificación automática. Escuche y preste atención. La Flota Conciencia aprueba su deseo de contribuir a la causa de la adquisición total de conocimiento. La Flota Conciencia está abierta a más donaciones de datos»."
        }
      ]
    },
    {
      "locale": "deDE",
      "text": "\"Automatische Benachrichtung wird wiedergegeben. Höret und befolget. Die Erkenntnisflotte ist erfreut über Euren Wunsch, zum Streben nach vollständiger Erkenntnis beizutragen. Die Erkenntnisflotte ist empfänglich für weitere Datenspenden.\"",
      "modification_date": "2023-10-17T09:07:50.2178797+00:00",
      "translation_comment": "",
      "translated_from": "enGB",
      "translation_date": "2023-10-17T09:07:50.2178799+00:00",
      "original_text": "\"Replaying automatic notification. Hear and heed. The Cognisance Fleet approves of your wish to contribute to the cause of total knowledge acquisition. The Cognisance Fleet is open to further data donations.\"",
      "traits": [
        {
          "trait": "Translated",
          "trait_date": "2023-10-17T09:07:50.2178817+00:00",
          "locale_text": "\"Automatische Benachrichtung wird wiedergegeben. Höret und befolget. Die Erkenntnisflotte ist erfreut über Euren Wunsch, zum Streben nach vollständiger Erkenntnis beizutragen. Die Erkenntnisflotte ist empfänglich für weitere Datenspenden.\""
        }
      ]
    },
    {
      "locale": "frFR",
      "text": "« Réitération de la notification automatique. Écoutez attentivement. La Flotte de la Connaissance approuve votre volonté de contribuer à l'acquisition de toutes connaissances. La Flotte de la Connaissance est ouverte au don de données supplémentaires. »",
      "modification_date": "2023-10-17T19:46:54.0979895+00:00",
      "translation_comment": "",
      "translated_from": "enGB",
      "translation_date": "2023-10-25T09:08:56.4594006+00:00",
      "original_text": "\"Replaying automatic notification. Hear and heed. The Cognisance Fleet approves of your wish to contribute to the cause of total knowledge acquisition. The Cognisance Fleet is open to further data donations.\"",
      "traits": [
        {
          "trait": "Translated",
          "trait_date": "2023-10-25T09:08:56.4594022+00:00",
          "locale_text": "« Réitération de la notification automatique. Écoutez attentivement. La Flotte de la Connaissance approuve votre volonté de contribuer à l'acquisition de toutes connaissances. La Flotte de la Connaissance est ouverte au don de données supplémentaires. »"
        }
      ]
    }
  ]
}