{
  "source": "ruRU",
  "key": "3cf87a5f-f07a-4af4-81c0-a1ba26256d2b",
  "ownerGuid": "9852af25b58542adad20a4dc09641fc4",
  "languages": [
    {
      "locale": "ruRU",
      "text": "\"Ходят слухи, что клан бригадиров, руководящий разбором завалов на руинах Сципионы, поддерживает с ними связь. Через них мы могли бы передать отступникам ваше слово... или заставить их выдать кочевые стойбища мятежников\".",
      "modification_date": "2023-07-12T20:26:10.9552438+00:00",
      "traits": []
    },
    {
      "locale": "enGB",
      "text": "\"Rumour has it that the foreman clan in charge of debris removal in the ruins of Scipione associates with these Vandals. We could pass on your words to the renegades via the foremen... or force them to disclose the locations of the rebels' nomadic camps.\"",
      "modification_date": "2024-02-16T10:29:56.251162+00:00",
      "translated_from": "ruRU",
      "translation_date": "2024-11-18T09:59:47.0380198+00:00",
      "original_text": "\"Ходят слухи, что клан бригадиров, руководящий разбором завалов на руинах Сципионы, поддерживает с ними связь. Через них мы могли бы передать отступникам ваше слово... или заставить их выдать кочевые стойбища мятежников\".",
      "traits": [
        {
          "trait": "Translated",
          "trait_date": "2023-08-04T05:18:26.8095931+00:00",
          "locale_text": "\"Rumour has it that the brigadier clan that is in charge of the debris clean up in the ruins of Scipione are keeping in touch with them. We could give the renegades your word via them... or get them to disclose the rebels' nomadic camps\"."
        },
        {
          "trait": "FG_tr",
          "trait_date": "2023-08-04T05:18:26.8095936+00:00",
          "locale_text": "\"Rumour has it that the brigadier clan that is in charge of the debris clean up in the ruins of Scipione are keeping in touch with them. We could give the renegades your word via them... or get them to disclose the rebels' nomadic camps\"."
        },
        {
          "trait": "Edited",
          "trait_date": "2023-09-11T10:33:52.8684093+00:00",
          "locale_text": "\"Rumour has it that the brigadier clan, in charge of debris removal in the ruins of Scipione, keep in contact. We could pass on your words to the renegades via the brigadiers... or force them to disclose the locations of the rebels' nomadic camps\"."
        },
        {
          "trait": "JL_ed",
          "trait_date": "2023-09-11T10:33:52.8684103+00:00",
          "locale_text": "\"Rumour has it that the brigadier clan, in charge of debris removal in the ruins of Scipione, keep in contact. We could pass on your words to the renegades via the brigadiers... or force them to disclose the locations of the rebels' nomadic camps\"."
        },
        {
          "trait": "Turkish",
          "trait_date": "2024-07-16T08:48:17.715834+00:00",
          "locale_text": "\"Rumour has it that the foreman clan in charge of debris removal in the ruins of Scipione associates with these Vandals. We could pass on your words to the renegades via the foremen... or force them to disclose the locations of the rebels' nomadic camps.\""
        },
        {
          "trait": "TK_rv",
          "trait_date": "2024-11-18T09:59:47.0380237+00:00",
          "locale_text": "\"Rumour has it that the foreman clan in charge of debris removal in the ruins of Scipione associates with these Vandals. We could pass on your words to the renegades via the foremen... or force them to disclose the locations of the rebels' nomadic camps.\""
        }
      ]
    },
    {
      "locale": "zhCN",
      "text": "“有传言说，负责清理希皮奥内废墟的领班氏族一直和引擎破坏者保持联系。我们可以通过那些领班，把您的话转达给那群叛徒……或者强迫领班透露那些叛徒移动营地的位置。”",
      "modification_date": "2024-10-21T12:34:46.2708041+00:00",
      "translated_from": "enGB",
      "translation_date": "2024-10-21T13:13:25.0207504+00:00",
      "original_text": "\"Rumour has it that the foreman clan in charge of debris removal in the ruins of Scipione associates with these Vandals. We could pass on your words to the renegades via the foremen... or force them to disclose the locations of the rebels' nomadic camps.\"",
      "traits": [
        {
          "trait": "Translated",
          "trait_date": "2024-10-21T13:13:25.0207509+00:00",
          "locale_text": "“有传言说，负责清理希皮奥内废墟的领班氏族一直和引擎破坏者保持联系。我们可以通过那些领班，把您的话转达给那群叛徒……或者强迫领班透露那些叛徒移动营地的位置。”"
        }
      ]
    },
    {
      "locale": "esES",
      "text": "«Se rumorea que el clan de los brigadistas, a cargo de la retirada de escombros en las ruinas de Escipión, está en contacto. Podríamos transmitir sus palabras a los renegados a través de los brigadistas... u obligarles a revelar la localización de los campamentos nómadas de los rebeldes».",
      "modification_date": "2023-10-02T15:43:27.4883983+00:00",
      "translated_from": "enGB",
      "translation_date": "2023-10-02T15:43:27.4883985+00:00",
      "original_text": "\"Rumour has it that the brigadier clan, in charge of debris removal in the ruins of Scipione, keep in contact. We could pass on your words to the renegades via the brigadiers... or force them to disclose the locations of the rebels' nomadic camps\".",
      "traits": [
        {
          "trait": "Translated",
          "trait_date": "2023-10-02T15:43:27.4883996+00:00",
          "locale_text": "«Se rumorea que el clan de los brigadistas, a cargo de la retirada de escombros en las ruinas de Escipión, está en contacto. Podríamos transmitir sus palabras a los renegados a través de los brigadistas... u obligarles a revelar la localización de los campamentos nómadas de los rebeldes»."
        }
      ]
    },
    {
      "locale": "jaJP",
      "text": "「噂によると、サイピオーネの廃墟の瓦礫を撤去している准将一族が連絡を取り合っているそうです。あなたの言葉を、准将を通じて反乱軍に伝えることができますよ...もしくは、反乱軍の遊牧キャンプの場所を明かすよう、強制することもできるだろう」",
      "modification_date": "2023-10-27T09:58:05.0191327+00:00",
      "translated_from": "enGB",
      "translation_date": "2023-10-27T09:58:05.0191332+00:00",
      "original_text": "\"Rumour has it that the brigadier clan, in charge of debris removal in the ruins of Scipione, keep in contact. We could pass on your words to the renegades via the brigadiers... or force them to disclose the locations of the rebels' nomadic camps\".",
      "traits": [
        {
          "trait": "Translated",
          "trait_date": "2023-10-27T09:58:05.0191355+00:00",
          "locale_text": "「噂によると、サイピオーネの廃墟の瓦礫を撤去している准将一族が連絡を取り合っているそうです。あなたの言葉を、准将を通じて反乱軍に伝えることができますよ...もしくは、反乱軍の遊牧キャンプの場所を明かすよう、強制することもできるだろう」"
        }
      ]
    },
    {
      "locale": "frFR",
      "text": "« À en croire la rumeur, le clan des Brigadiers chargé du ramassage des gravats dans les ruines de Scipione serait en contact avec eux. Nous pourrions les utiliser pour transmettre un message aux renégats ou les obliger à révéler l'emplacement des camps rebelles. »",
      "modification_date": "2023-11-19T21:10:39.5141691+00:00",
      "translated_from": "enGB",
      "translation_date": "2023-11-19T21:10:39.5141698+00:00",
      "original_text": "\"Rumour has it that the brigadier clan, in charge of debris removal in the ruins of Scipione, keep in contact. We could pass on your words to the renegades via the brigadiers... or force them to disclose the locations of the rebels' nomadic camps.\"",
      "traits": [
        {
          "trait": "Translated",
          "trait_date": "2023-11-19T21:10:39.514172+00:00",
          "locale_text": "« À en croire la rumeur, le clan des Brigadiers chargé du ramassage des gravats dans les ruines de Scipione serait en contact avec eux. Nous pourrions les utiliser pour transmettre un message aux renégats ou les obliger à révéler l'emplacement des camps rebelles. »"
        }
      ]
    },
    {
      "locale": "deDE",
      "text": "\"Gerüchten zufolge steht der Brigadierclan, der für die Beseitigung des Schutts in den Ruinen von Scipion verantwortlich ist, noch in Kontakt mit ihnen. Die Brigadiere könnten Eure Worte an die Abtrünnigen weitergeben ... Oder wir könnten sie zwingen, uns die Koordinaten der Nomadenlager der Ketzer zu nennen.\"",
      "modification_date": "2023-10-23T09:47:25.0460292+00:00",
      "translated_from": "enGB",
      "translation_date": "2023-10-23T09:47:25.0460298+00:00",
      "original_text": "\"Rumour has it that the brigadier clan, in charge of debris removal in the ruins of Scipione, keep in contact. We could pass on your words to the renegades via the brigadiers... or force them to disclose the locations of the rebels' nomadic camps.\"",
      "traits": [
        {
          "trait": "Translated",
          "trait_date": "2023-10-23T09:47:25.0460317+00:00",
          "locale_text": "\"Gerüchten zufolge steht der Brigadierclan, der für die Beseitigung des Schutts in den Ruinen von Scipion verantwortlich ist, noch in Kontakt mit ihnen. Die Brigadiere könnten Eure Worte an die Abtrünnigen weitergeben ... Oder wir könnten sie zwingen, uns die Koordinaten der Nomadenlager der Ketzer zu nennen.\""
        }
      ]
    },
    {
      "locale": "trTR",
      "text": "\"Söylentilere göre Scipione harabelerinde enkaz kaldırmayla görevli ustabaşı klanının bu Vandallarla münasebeti var. Ustabaşılar aracılığıyla bu hainlere sözlerinizi iletebiliriz ya da... İsyancıların göçebe kamplarının yerini söylemeleri için onları zorlayabiliriz.\"",
      "modification_date": "2024-11-15T11:55:59.4235285+00:00",
      "translated_from": "enGB",
      "translation_date": "2024-11-15T11:55:59.4235292+00:00",
      "original_text": "\"Rumour has it that the foreman clan in charge of debris removal in the ruins of Scipione associates with these Vandals. We could pass on your words to the renegades via the foremen... or force them to disclose the locations of the rebels' nomadic camps.\""
    }
  ],
  "string_traits": [
    {
      "trait": "Minor",
      "trait_date": "2024-05-05T09:41:57.2457121+00:00",
      "locale_text": ""
    },
    {
      "trait": "яп_апдейт",
      "trait_date": "2024-10-11T08:28:52.8083409+00:00",
      "locale_text": ""
    },
    {
      "trait": "хроники",
      "trait_date": "2024-11-18T09:48:43.2752007+00:00",
      "locale_text": ""
    },
    {
      "trait": "ворлды_минор",
      "trait_date": "2024-11-27T14:22:09.6999057+00:00",
      "locale_text": ""
    }
  ]
}