{
  "source": "ruRU",
  "key": "9858a133-70e5-4761-be0c-c18aef99d098",
  "ownerGuid": "3a1b5073f57d48959bc469de16a645ad",
  "languages": [
    {
      "locale": "ruRU",
      "text": "\"Ваша Светлость! Чудовищный шторм разразился на Янусе! Апокалиптические аномалии терзают наш агромир, и эпицентр их — оскверненный сектор! Необходимо что-то делать, пока вся колония не погибла! Необходимо... найти источник этого лиходейства!\"",
      "modification_date": "2023-08-02T08:56:29.1592879+03:00",
      "traits": []
    },
    {
      "locale": "enGB",
      "text": "\"Your {mf|Lordship|Ladyship}! A monstrous storm has broken out on Janus! Apocalyptic anomalies are tearing our agri-world apart, and their epicentre is in the corrupted sector! Something must be done before the whole colony is destroyed! We must find the source of this... madness!\"",
      "modification_date": "2024-11-18T09:59:50.2933852+00:00",
      "translated_from": "ruRU",
      "translation_date": "2024-11-26T13:53:38.9999242+00:00",
      "original_text": "\"Ваша Светлость! Чудовищный шторм разразился на Янусе! Апокалиптические аномалии терзают наш агромир, и эпицентр их — оскверненный сектор! Необходимо что-то делать, пока вся колония не погибла! Необходимо... найти источник этого лиходейства!\"",
      "traits": [
        {
          "trait": "Translated",
          "trait_date": "2023-08-04T05:18:28.8438141+00:00",
          "locale_text": "\"Your {mf|Lordship|Ladyship}! A monstrous storm has broken out on Janus! The apocalyptic anomalies are tearing our agri-world apart, and their epicentre is a desecrated sector! Something must be done before the whole colony is destroyed! We have... to find the source of this madness!\""
        },
        {
          "trait": "FG_tr",
          "trait_date": "2023-08-04T05:18:28.8438147+00:00",
          "locale_text": "\"Your {mf|Lordship|Ladyship}! A monstrous storm has broken out on Janus! The apocalyptic anomalies are tearing our agri-world apart, and their epicentre is a desecrated sector! Something must be done before the whole colony is destroyed! We have... to find the source of this madness!\""
        },
        {
          "trait": "Edited",
          "trait_date": "2024-11-26T09:30:31.7790276+00:00",
          "locale_text": "\"Your {mf|Lordship|Ladyship}! A monstrous storm has broken out on Janus! Apocalyptic anomalies are tearing our agri-world apart, and their epicentre is in the corrupted sector! Something must be done before the whole colony is destroyed! We must find the source of this... madness!\""
        },
        {
          "trait": "JL_ed",
          "trait_date": "2023-09-11T10:33:55.0746265+00:00",
          "locale_text": "\"Your {mf|Lordship|Ladyship}! A monstrous storm has broken out on Janus! The apocalyptic anomalies are tearing our agri-world apart, and their epicentre is in the desecrated sector! Something must be done before the whole colony is destroyed! We have... to find the source of this madness!\""
        },
        {
          "trait": "Turkish",
          "trait_date": "2024-07-16T08:48:21.6860064+00:00",
          "locale_text": "\"Your {mf|Lordship|Ladyship}! A monstrous storm has broken out on Janus! The apocalyptic anomalies are tearing our agri-world apart, and their epicentre is in the desecrated sector! Something must be done before the whole colony is destroyed! We have... to find the source of this madness!\""
        },
        {
          "trait": "TK_rv",
          "trait_date": "2024-11-26T13:53:38.9999259+00:00",
          "locale_text": "\"Your {mf|Lordship|Ladyship}! A monstrous storm has broken out on Janus! Apocalyptic anomalies are tearing our agri-world apart, and their epicentre is in the corrupted sector! Something must be done before the whole colony is destroyed! We must find the source of this... madness!\""
        },
        {
          "trait": "AD_ed",
          "trait_date": "2024-11-26T09:30:31.779028+00:00",
          "locale_text": "\"Your {mf|Lordship|Ladyship}! A monstrous storm has broken out on Janus! Apocalyptic anomalies are tearing our agri-world apart, and their epicentre is in the corrupted sector! Something must be done before the whole colony is destroyed! We must find the source of this... madness!\""
        },
        {
          "trait": "Reviewed",
          "trait_date": "2024-11-26T13:53:38.9999256+00:00",
          "locale_text": "\"Your {mf|Lordship|Ladyship}! A monstrous storm has broken out on Janus! Apocalyptic anomalies are tearing our agri-world apart, and their epicentre is in the corrupted sector! Something must be done before the whole colony is destroyed! We must find the source of this... madness!\""
        }
      ]
    },
    {
      "locale": "zhCN",
      "text": "“大人！一场极其凶暴的风暴袭击了加努斯！世界末日般的异象正在撕裂我们的农业世界，而它们的中心就在那片亵渎区域！我们得赶在整个殖民地被摧毁之前做点什么！我们必须……必须找到这疯狂的根源！”",
      "modification_date": "2023-11-01T11:04:03.5285032+00:00",
      "translated_from": "enGB",
      "translation_date": "2023-11-01T11:04:03.5285045+00:00",
      "original_text": "\"Your {mf|Lordship|Ladyship}! A monstrous storm has broken out on Janus! The apocalyptic anomalies are tearing our agri-world apart, and their epicentre is in the desecrated sector! Something must be done before the whole colony is destroyed! We have... to find the source of this madness!\"",
      "traits": [
        {
          "trait": "Translated",
          "trait_date": "2023-11-01T11:04:03.5285095+00:00",
          "locale_text": "“大人！一场极其凶暴的风暴袭击了加努斯！世界末日般的异象正在撕裂我们的农业世界，而它们的中心就在那片亵渎区域！我们得赶在整个殖民地被摧毁之前做点什么！我们必须……必须找到这疯狂的根源！”"
        },
        {
          "trait": "сами",
          "trait_date": "2024-12-09T12:59:54.0382062+00:00",
          "locale_text": "“大人！一场极其凶暴的风暴袭击了加努斯！世界末日般的异象正在撕裂我们的农业世界，而它们的中心就在那片亵渎区域！我们得赶在整个殖民地被摧毁之前做点什么！我们必须……必须找到这疯狂的根源！”"
        }
      ]
    },
    {
      "locale": "esES",
      "text": "«¡Mi{mf|lord|lady}! ¡Una monstruosa tormenta se ha desatado en Janus! Las anomalías apocalípticas están destrozando nuestro agromundo, ¡y su epicentro está en el sector profanado! ¡Hay que hacer algo antes de que toda la colonia sea destruida! Tenemos... ¡Tenemos que encontrar la fuente de esta locura!».",
      "modification_date": "2023-10-02T15:43:29.0452754+00:00",
      "translated_from": "enGB",
      "translation_date": "2023-10-02T15:43:29.0452756+00:00",
      "original_text": "\"Your {mf|Lordship|Ladyship}! A monstrous storm has broken out on Janus! The apocalyptic anomalies are tearing our agri-world apart, and their epicentre is in the desecrated sector! Something must be done before the whole colony is destroyed! We have... to find the source of this madness!\"",
      "traits": [
        {
          "trait": "Translated",
          "trait_date": "2023-10-02T15:43:29.0452763+00:00",
          "locale_text": "«¡Mi{mf|lord|lady}! ¡Una monstruosa tormenta se ha desatado en Janus! Las anomalías apocalípticas están destrozando nuestro agromundo, ¡y su epicentro está en el sector profanado! ¡Hay que hacer algo antes de que toda la colonia sea destruida! Tenemos... ¡Tenemos que encontrar la fuente de esta locura!»."
        }
      ]
    },
    {
      "locale": "jaJP",
      "text": "「陛下！ヤヌスに巨大な嵐が発生しました！絶望的なアノマリーが農業惑星を引き裂き、その震央は冒涜されたセクターにあります！コロニー全体が破壊される前に何か手を打たなければなりません！この...狂気の源を探し当てねばなりません！」",
      "modification_date": "2023-10-27T09:58:07.0677583+00:00",
      "translated_from": "enGB",
      "translation_date": "2023-10-27T09:58:07.0677585+00:00",
      "original_text": "\"Your {mf|Lordship|Ladyship}! A monstrous storm has broken out on Janus! The apocalyptic anomalies are tearing our agri-world apart, and their epicentre is in the desecrated sector! Something must be done before the whole colony is destroyed! We have... to find the source of this madness!\"",
      "traits": [
        {
          "trait": "Translated",
          "trait_date": "2023-10-27T09:58:07.0677599+00:00",
          "locale_text": "「陛下！ヤヌスに巨大な嵐が発生しました！絶望的なアノマリーが農業惑星を引き裂き、その震央は冒涜されたセクターにあります！コロニー全体が破壊される前に何か手を打たなければなりません！この...狂気の源を探し当てねばなりません！」"
        },
        {
          "trait": "сами",
          "trait_date": "2024-12-09T13:01:04.8816839+00:00",
          "locale_text": "「陛下！ヤヌスに巨大な嵐が発生しました！絶望的なアノマリーが農業惑星を引き裂き、その震央は冒涜されたセクターにあります！コロニー全体が破壊される前に何か手を打たなければなりません！この...狂気の源を探し当てねばなりません！」"
        }
      ]
    },
    {
      "locale": "frFR",
      "text": "« Votre Seigneurie ! Une tempête gigantesque fait rage sur Janus ! Des anomalies apocalyptiques réduisent nos infrastructures agricoles en miettes, et l'épicentre du phénomène est devenu une zone totalement corrompue ! Il faut intervenir avant que la colonie tout entière disparaisse ! Il faut trouver la source de cette... folie ! »",
      "modification_date": "2024-12-09T10:20:09.9431564+00:00",
      "translated_from": "enGB",
      "translation_date": "2024-12-09T10:20:09.9431568+00:00",
      "original_text": "\"Your {mf|Lordship|Ladyship}! A monstrous storm has broken out on Janus! Apocalyptic anomalies are tearing our agri-world apart, and their epicentre is in the corrupted sector! Something must be done before the whole colony is destroyed! We must find the source of this... madness!\"",
      "traits": [
        {
          "trait": "Translated",
          "trait_date": "2024-12-09T10:20:09.9431582+00:00",
          "locale_text": "« Votre Seigneurie ! Une tempête gigantesque fait rage sur Janus ! Des anomalies apocalyptiques réduisent nos infrastructures agricoles en miettes, et l'épicentre du phénomène est devenu une zone totalement corrompue ! Il faut intervenir avant que la colonie tout entière disparaisse ! Il faut trouver la source de cette... folie ! »"
        }
      ]
    },
    {
      "locale": "deDE",
      "text": "\"Eure {mf|Lordschaft|Ladyschaft}! Auf Janus ist ein monströser Sturm ausgebrochen! Die apokalyptischen Anomalien zerreißen unsere Agrarwelt, und ihr Epizentrum liegt im entweihten Sektor! Irgendetwas muss geschehen, bevor die ganze Kolonie zerstört wird! Wir müssen ... die Quelle dieses Irrsinns finden!\"",
      "modification_date": "2023-10-23T09:47:29.1117077+00:00",
      "translated_from": "enGB",
      "translation_date": "2023-10-23T09:47:29.1117084+00:00",
      "original_text": "\"Your {mf|Lordship|Ladyship}! A monstrous storm has broken out on Janus! The apocalyptic anomalies are tearing our agri-world apart, and their epicentre is in the desecrated sector! Something must be done before the whole colony is destroyed! We have... to find the source of this madness!\"",
      "traits": [
        {
          "trait": "Translated",
          "trait_date": "2023-10-23T09:47:29.11171+00:00",
          "locale_text": "\"Eure {mf|Lordschaft|Ladyschaft}! Auf Janus ist ein monströser Sturm ausgebrochen! Die apokalyptischen Anomalien zerreißen unsere Agrarwelt, und ihr Epizentrum liegt im entweihten Sektor! Irgendetwas muss geschehen, bevor die ganze Kolonie zerstört wird! Wir müssen ... die Quelle dieses Irrsinns finden!\""
        },
        {
          "trait": "сами",
          "trait_date": "2024-12-09T13:02:57.453765+00:00",
          "locale_text": "\"Eure {mf|Lordschaft|Ladyschaft}! Auf Janus ist ein monströser Sturm ausgebrochen! Die apokalyptischen Anomalien zerreißen unsere Agrarwelt, und ihr Epizentrum liegt im entweihten Sektor! Irgendetwas muss geschehen, bevor die ganze Kolonie zerstört wird! Wir müssen ... die Quelle dieses Irrsinns finden!\""
        }
      ]
    },
    {
      "locale": "trTR",
      "text": "\"{mf|Lord|Leydi} Hazretleri! Janus'ta korkunç bir fırtına patlak verdi. Kıyametvari anomaliler, zirai dünyamızı altüst ediyor. Merkez üssü ise yozlaşmış sektörde! Tüm koloni yok edilmeden önce bir şeyler yapmak gerekiyor! Bu deliliğin kaynağını bulmalıyız!\"",
      "modification_date": "2024-12-13T13:31:46.4296713+00:00",
      "translated_from": "enGB",
      "translation_date": "2024-12-13T13:31:46.4296717+00:00",
      "original_text": "\"Your {mf|Lordship|Ladyship}! A monstrous storm has broken out on Janus! Apocalyptic anomalies are tearing our agri-world apart, and their epicentre is in the corrupted sector! Something must be done before the whole colony is destroyed! We must find the source of this... madness!\"",
      "traits": [
        {
          "trait": "Translated",
          "trait_date": "2024-12-13T13:31:46.4296734+00:00",
          "locale_text": "\"{mf|Lord|Leydi} Hazretleri! Janus'ta korkunç bir fırtına patlak verdi. Kıyametvari anomaliler, zirai dünyamızı altüst ediyor. Merkez üssü ise yozlaşmış sektörde! Tüm koloni yok edilmeden önce bir şeyler yapmak gerekiyor! Bu deliliğin kaynağını bulmalıyız!\""
        }
      ]
    }
  ],
  "string_traits": [
    {
      "trait": "Minor",
      "trait_date": "2024-12-03T09:04:46.9781225+00:00",
      "locale_text": ""
    },
    {
      "trait": "ворлды_минор",
      "trait_date": "2024-11-27T14:22:11.1202797+00:00",
      "locale_text": ""
    },
    {
      "trait": "тур_апдейт",
      "trait_date": "2024-12-03T08:16:07.4341984+00:00",
      "locale_text": ""
    },
    {
      "trait": "отдать_тур",
      "trait_date": "2024-12-03T08:43:48.7404674+00:00",
      "locale_text": ""
    },
    {
      "trait": "тур_апд_финал",
      "trait_date": "2024-12-03T09:11:23.4492737+00:00",
      "locale_text": ""
    },
    {
      "trait": "колон",
      "trait_date": "2024-12-10T10:30:55.6573589+00:00",
      "locale_text": ""
    }
  ]
}