{
  "source": "ruRU",
  "key": "afbae6a4-4708-4447-889a-d0bf57418534",
  "ownerGuid": "814441b681634383ba24f3d40fc3caba",
  "languages": [
    {
      "locale": "ruRU",
      "text": "Архмилитантами, являющимися специалистами по всем видам оружия, могут стать {g|Encyclopedia:CareerFighterGlossary}воины{/g}, {g|Encyclopedia:CareerMarksmanGlossary}солдаты{/g} и {g|Encyclopedia:CareerBladedancerGlossary}танцоры смерти{/g}.",
      "modification_date": "2024-11-29T18:40:37.4633488+00:00",
      "translation_comment": "",
      "traits": []
    },
    {
      "locale": "enGB",
      "text": "{g|Encyclopedia:CareerBladedancerGlossary}Bladedancers{/g}, {g|Encyclopedia:CareerMarksmanGlossary}Soldiers{/g}, and {g|Encyclopedia:CareerFighterGlossary}Warriors{/g} can become Arch-Militants, versatile experts who utilise different types of weapons to maximum efficiency.",
      "modification_date": "2024-11-29T18:29:45.0741555+00:00",
      "translation_comment": "",
      "translated_from": "ruRU",
      "translation_date": "2023-09-13T11:06:57.8732075+00:00",
      "original_text": "Ветеранами, являющимися специалистами по всем видам оружия, могут стать стрелки и воины.",
      "traits": [
        {
          "trait": "Translated",
          "trait_date": "2023-09-13T11:06:57.8732088+00:00",
          "locale_text": "Marksmen and Fighters can become Veterans, versatile experts who utilise different types of weapons with maximum efficiency."
        },
        {
          "trait": "TK_tr",
          "trait_date": "2023-09-13T11:06:57.873209+00:00",
          "locale_text": "Marksmen and Fighters can become Veterans, versatile experts who utilise different types of weapons with maximum efficiency."
        },
        {
          "trait": "Edited",
          "trait_date": "2024-12-02T09:55:16.9266107+00:00",
          "locale_text": "{g|Encyclopedia:CareerBladedancerGlossary}Bladedancers{/g}, {g|Encyclopedia:CareerMarksmanGlossary}Soldiers{/g}, and {g|Encyclopedia:CareerFighterGlossary}Warriors{/g} can become Arch-Militants, versatile experts who utilise different types of weapons to maximum efficiency."
        },
        {
          "trait": "JL_ed",
          "trait_date": "2024-07-26T12:05:07.4307288+00:00",
          "locale_text": "Soldiers and {g|Encyclopedia:CareerFighterGlossary}Warriors{/g} can become Arch-Militants, versatile experts who utilise different types of weapons to maximum efficiency."
        },
        {
          "trait": "Turkish",
          "trait_date": "2024-09-19T15:14:24.9101524+00:00",
          "locale_text": "Soldiers and {g|Encyclopedia:CareerFighterGlossary}Warriors{/g} can become Arch-Militants, versatile experts who utilise different types of weapons to maximum efficiency."
        }
      ]
    },
    {
      "locale": "deDE",
      "text": "{g|Encyclopedia:CareerBladedancerGlossary}Klingentänzer{/g}, {g|Encyclopedia:CareerMarksmanGlossary}Soldaten{/g} und {g|Encyclopedia:CareerFighterGlossary}Krieger{/g} können zu Erzmilitanten werden, vielseitige Experten, die verschiedene Waffenarten nutzen, um die Effizienz zu maximieren.",
      "modification_date": "2024-12-12T16:03:48.682553+00:00",
      "translation_comment": "",
      "translated_from": "enGB",
      "translation_date": "2024-11-26T09:42:22.0895032+00:00",
      "original_text": "{g|Encyclopedia:CareerBladedancerGlossary}Bladedancers{/g}, {g|Encyclopedia:CareerMarksmanGlossary}Soldiers{/g}, and {g|Encyclopedia:CareerFighterGlossary}Warriors{/g} can become Arch-Militants, versatile experts who utilise different types of weapons to maximum efficiency.",
      "traits": [
        {
          "trait": "Translated",
          "trait_date": "2023-10-18T19:10:58.5069286+00:00",
          "locale_text": "Scharfschützen und Kämpfer können zu Veteranen werden, vielseitige Experten, die verschiedene Waffenarten nutzen, um die Effizienz zu maximieren."
        },
        {
          "trait": "сами",
          "trait_date": "2024-12-09T13:02:55.4483149+00:00",
          "locale_text": "Soldaten und {g|Encyclopedia:CareerFighterGlossary}Krieger{/g} können zu Erzmilitanten werden, vielseitige Experten, die verschiedene Waffenarten nutzen, um die Effizienz zu maximieren."
        }
      ]
    },
    {
      "locale": "frFR",
      "text": "Les soldats et les {g|Encyclopedia:CareerFighterGlossary}guerriers{/g} peuvent devenir des archimilitants, des experts polyvalents capables d'exploiter le plein potentiel de divers types d'armes.",
      "modification_date": "2024-09-11T10:10:03.9581252+00:00",
      "translation_comment": "",
      "translated_from": "enGB",
      "translation_date": "2024-09-11T10:10:03.9581257+00:00",
      "original_text": "Soldiers and {g|Encyclopedia:CareerFighterGlossary}Warriors{/g} can become Arch-Militants, versatile experts who utilise different types of weapons to maximum efficiency.",
      "traits": [
        {
          "trait": "Translated",
          "trait_date": "2024-09-11T10:10:03.9581279+00:00",
          "locale_text": "Les soldats et les {g|Encyclopedia:CareerFighterGlossary}guerriers{/g} peuvent devenir des archimilitants, des experts polyvalents capables d'exploiter le plein potentiel de divers types d'armes."
        },
        {
          "trait": "Updates_Sent",
          "trait_date": "2024-08-26T09:12:37.1717797+00:00",
          "locale_text": "Les Tireurs d'Élite et les {g|Encyclopedia:CareerFighterGlossary}combattants{/g} peuvent devenir archimilitants, des experts polyvalents capables de tirer pleinement parti de différents types d'armes."
        },
        {
          "trait": "Reviewed",
          "trait_date": "2024-09-11T10:10:03.9581286+00:00",
          "locale_text": "Les soldats et les {g|Encyclopedia:CareerFighterGlossary}guerriers{/g} peuvent devenir des archimilitants, des experts polyvalents capables d'exploiter le plein potentiel de divers types d'armes."
        },
        {
          "trait": "сами",
          "trait_date": "2024-12-09T13:01:48.8244159+00:00",
          "locale_text": "Les soldats et les {g|Encyclopedia:CareerFighterGlossary}guerriers{/g} peuvent devenir des archimilitants, des experts polyvalents capables d'exploiter le plein potentiel de divers types d'armes."
        }
      ]
    },
    {
      "locale": "zhCN",
      "text": "士兵与{g|Encyclopedia:CareerFighterGlossary}战士{/g}可以晋级为首席战士。首席战士是多才多艺的战斗专家，擅长利用各种不同的武器，从而最大限度提高战斗效率。",
      "modification_date": "2024-03-25T20:09:13.0151158+00:00",
      "translation_comment": "",
      "translated_from": "enGB",
      "translation_date": "2024-10-21T13:13:23.2538246+00:00",
      "original_text": "Soldiers and {g|Encyclopedia:CareerFighterGlossary}Warriors{/g} can become Arch-Militants, versatile experts who utilise different types of weapons to maximum efficiency.",
      "traits": [
        {
          "trait": "Translated",
          "trait_date": "2024-10-21T13:13:23.2538253+00:00",
          "locale_text": "士兵与{g|Encyclopedia:CareerFighterGlossary}战士{/g}可以晋级为首席战士。首席战士是多才多艺的战斗专家，擅长利用各种不同的武器，从而最大限度提高战斗效率。"
        },
        {
          "trait": "сами",
          "trait_date": "2024-12-09T12:59:52.7141185+00:00",
          "locale_text": "士兵与{g|Encyclopedia:CareerFighterGlossary}战士{/g}可以晋级为首席战士。首席战士是多才多艺的战斗专家，擅长利用各种不同的武器，从而最大限度提高战斗效率。"
        }
      ]
    },
    {
      "locale": "jaJP",
      "text": "兵士と{g|Encyclopedia:CareerFighterGlossary}戦士{/g}は、異なる種類の武器を多彩に使用することのできる専門家であるアーク・ミリタントになることができる。",
      "modification_date": "2024-10-21T10:03:50.5622521+00:00",
      "translation_comment": "",
      "translated_from": "enGB",
      "translation_date": "2024-10-21T10:03:50.5622524+00:00",
      "original_text": "Soldiers and {g|Encyclopedia:CareerFighterGlossary}Warriors{/g} can become Arch-Militants, versatile experts who utilise different types of weapons to maximum efficiency.",
      "traits": [
        {
          "trait": "Translated",
          "trait_date": "2023-11-09T10:06:53.010686+00:00",
          "locale_text": "マークスマンとファイターは、異なる種類の武器を最高の効率で使用する多才な専門家である古参になることができる。"
        },
        {
          "trait": "сами",
          "trait_date": "2024-12-09T13:01:03.2468314+00:00",
          "locale_text": "兵士と{g|Encyclopedia:CareerFighterGlossary}戦士{/g}は、異なる種類の武器を多彩に使用することのできる専門家であるアーク・ミリタントになることができる。"
        }
      ]
    },
    {
      "locale": "esES",
      "text": "Los {g|Encyclopedia:CareerBladedancerGlossary}hojas danzantes{/g}, los {g|Encyclopedia:CareerMarksmanGlossary}soldados{/g} y los {g|Encyclopedia:CareerFighterGlossary}guerreros{/g} pueden convertirse en Archimilitantes, expertos todoterreno que sacan el máximo partido a todo tipo de armas.",
      "modification_date": "2024-12-16T08:38:24.5535488+00:00",
      "translation_comment": "",
      "translated_from": "enGB",
      "translation_date": "2024-12-16T08:38:24.5535491+00:00",
      "original_text": "{g|Encyclopedia:CareerBladedancerGlossary}Bladedancers{/g}, {g|Encyclopedia:CareerMarksmanGlossary}Soldiers{/g}, and {g|Encyclopedia:CareerFighterGlossary}Warriors{/g} can become Arch-Militants, versatile experts who utilise different types of weapons to maximum efficiency.",
      "traits": [
        {
          "trait": "Translated",
          "trait_date": "2024-12-16T08:38:24.5535499+00:00",
          "locale_text": "Los {g|Encyclopedia:CareerBladedancerGlossary}hojas danzantes{/g}, los {g|Encyclopedia:CareerMarksmanGlossary}soldados{/g} y los {g|Encyclopedia:CareerFighterGlossary}guerreros{/g} pueden convertirse en Archimilitantes, expertos todoterreno que sacan el máximo partido a todo tipo de armas."
        },
        {
          "trait": "Updates_Sent",
          "trait_date": "2024-08-26T09:02:16.5870195+00:00",
          "locale_text": "Los tiradores de élite y los {g|Encyclopedia:CareerFighterGlossary}guerreros{/g} pueden convertirse en Archimilitantes, expertos todoterreno que sacan el máximo partido a todo tipo de armas."
        }
      ]
    },
    {
      "locale": "trTR",
      "text": "{g|Encyclopedia:CareerBladedancerGlossary}Kılıç Dansçısı{/g}, {g|Encyclopedia:CareerMarksmanGlossary}Asker{/g} ve {g|Encyclopedia:CareerFighterGlossary}Savaşçılar{/g}; farklı silah türlerinden maksimum düzeyde faydalanabilen çok yönlü uzmanlar olan Başmilitan'a dönüşebilirler.",
      "modification_date": "2024-12-13T13:31:45.0211719+00:00",
      "translated_from": "enGB",
      "translation_date": "2024-12-13T13:31:45.0211727+00:00",
      "original_text": "{g|Encyclopedia:CareerBladedancerGlossary}Bladedancers{/g}, {g|Encyclopedia:CareerMarksmanGlossary}Soldiers{/g}, and {g|Encyclopedia:CareerFighterGlossary}Warriors{/g} can become Arch-Militants, versatile experts who utilise different types of weapons to maximum efficiency.",
      "traits": [
        {
          "trait": "Translated",
          "trait_date": "2024-12-13T13:31:45.021175+00:00",
          "locale_text": "{g|Encyclopedia:CareerBladedancerGlossary}Kılıç Dansçısı{/g}, {g|Encyclopedia:CareerMarksmanGlossary}Asker{/g} ve {g|Encyclopedia:CareerFighterGlossary}Savaşçılar{/g}; farklı silah türlerinden maksimum düzeyde faydalanabilen çok yönlü uzmanlar olan Başmilitan'a dönüşebilirler."
        }
      ]
    }
  ],
  "string_traits": [
    {
      "trait": "OtherLocs_ToReview",
      "trait_date": "2023-09-26T16:59:02.009826+00:00",
      "locale_text": ""
    },
    {
      "trait": "Minor",
      "trait_date": "2024-12-03T08:56:15.6196271+00:00",
      "locale_text": ""
    },
    {
      "trait": "яп_апдейт",
      "trait_date": "2024-10-11T08:28:52.5898706+00:00",
      "locale_text": ""
    },
    {
      "trait": "японский_отдать",
      "trait_date": "2024-10-11T11:34:37.8975444+00:00",
      "locale_text": ""
    },
    {
      "trait": "обновление_яп",
      "trait_date": "2024-10-11T11:52:06.9214987+00:00",
      "locale_text": ""
    },
    {
      "trait": "механ_уехал",
      "trait_date": "2024-10-11T12:06:58.2990236+00:00",
      "locale_text": ""
    },
    {
      "trait": "языки_пост13",
      "trait_date": "2024-12-02T09:55:36.5848194+00:00",
      "locale_text": ""
    },
    {
      "trait": "тур_апдейт",
      "trait_date": "2024-12-03T08:13:56.6163122+00:00",
      "locale_text": ""
    },
    {
      "trait": "отдать_тур",
      "trait_date": "2024-12-03T08:43:46.9906141+00:00",
      "locale_text": ""
    },
    {
      "trait": "тур_апд_финал",
      "trait_date": "2024-12-03T09:11:21.8860739+00:00",
      "locale_text": ""
    },
    {
      "trait": "взять_es",
      "trait_date": "2024-12-10T10:58:34.3854562+00:00",
      "locale_text": ""
    },
    {
      "trait": "взять_zh",
      "trait_date": "2024-12-16T12:00:06.8801889+00:00",
      "locale_text": ""
    },
    {
      "trait": "взять_кит",
      "trait_date": "2024-12-17T11:42:38.0919174+00:00",
      "locale_text": ""
    }
  ]
}