{
  "source": "ruRU",
  "key": "020b3ce0-4130-4b40-9b96-9327ad271f65",
  "speaker": "YrlietCompanion",
  "speakerGender": "Female",
  "ownerGuid": "dbd9755ddf2f4d9a98ea64ff40a839b5",
  "languages": [
    {
      "locale": "ruRU",
      "text": "\"Что ж, элантах. Раз воля твоя превыше человеческих законов о ксеносах, и рядом с тобой мне не грозит расправа — я принимаю твое предложение\".",
      "modification_date": "2024-04-17T17:23:21.2713772+00:00",
      "translation_comment": "Компаньон попадает в ростер",
      "traits": [
        {
          "trait": "CheckMe",
          "trait_date": "2021-06-02T16:46:34.6888797+00:00",
          "locale_text": "\"Что ж. Раз воля твоя превыше человеческих законов о ксеносах, и рядом с тобой мне не грозит расправа — я принимаю твое предложение\". {n}Ирлиэт прикусывает губу и ехидно смеется.{/n} \"О, не сомневаюсь, Ульран будет просто вне себя...\""
        }
      ]
    },
    {
      "locale": "enGB",
      "text": "\"Well, elantach. Since your will supersedes human laws on xenos, and I will face no reprisals while I am by your side — I accept your offer.\"",
      "modification_date": "2022-10-17T23:15:31.598019+03:00",
      "translated_from": "ruRU",
      "translation_date": "2022-10-17T23:16:06.6640665+03:00",
      "original_text": "\"Что ж, элантах. Раз воля твоя превыше человеческих законов о ксеносах, и рядом с тобой мне не грозит расправа — я принимаю твое предложение\".",
      "traits": [
        {
          "trait": "Translated",
          "trait_date": "2021-08-12T18:54:33.7937985+03:00",
          "locale_text": "\"Well, then. Since your will supersedes human laws on Xenos, and I will face no reprisals while I am by your side — I accept your offer.\" {n}For a split second, Yrliet sheds her serious demeanor and laughs mischievously.{/n} \"Oh, Ulrahn will be beside himself...\""
        },
        {
          "trait": "Edited",
          "trait_date": "2022-02-24T09:57:23.7358867+03:00",
          "locale_text": "\"Well, then. Since your will supersedes human laws on Xenos, and I will face no reprisals while I am by your side — I accept your offer.\" {n}For a split second, Yrliet sheds her serious demeanor and laughs mischievously.{/n} \"Oh, Ulrahn will be beside himself...\""
        },
        {
          "trait": "AD_tr_ed",
          "trait_date": "2021-08-12T18:54:33.7937996+03:00",
          "locale_text": "\"Well, then. Since your will supersedes human laws on Xenos, and I will face no reprisals while I am by your side — I accept your offer.\" {n}For a split second, Yrliet sheds her serious demeanor and laughs mischievously.{/n} \"Oh, Ulrahn will be beside himself...\""
        },
        {
          "trait": "Turkish",
          "trait_date": "2023-10-25T13:13:08.3219826+00:00",
          "locale_text": "\"Well, elantach. Since your will supersedes human laws on xenos, and I will face no reprisals while I am by your side — I accept your offer.\""
        }
      ]
    },
    {
      "locale": "zhCN",
      "text": "“好吧，外界人。既然你的意志比人类对待异形的律法更为优先，而且我在你身边时不用担心遭到报复，我愿意接受你的提议。”",
      "modification_date": "2023-05-22T12:04:41.1221497+03:00",
      "translated_from": "enGB",
      "translation_date": "2023-05-22T12:04:41.1221499+03:00",
      "original_text": "\"Well, elantach. Since your will supersedes human laws on xenos, and I will face no reprisals while I am by your side — I accept your offer.\"",
      "traits": [
        {
          "trait": "Translated",
          "trait_date": "2023-05-22T12:04:41.1221508+03:00",
          "locale_text": "“好吧，外界人。既然你的意志比人类对待异形的律法更为优先，而且我在你身边时不用担心遭到报复，我愿意接受你的提议。”"
        }
      ]
    },
    {
      "locale": "esES",
      "text": "«De acuerdo, elantach. Ya que tu voluntad se antepone a las leyes humanas sobre los xenos y, por tanto, no sufriré represalias mientras esté a tu lado... acepto tu oferta».",
      "modification_date": "2023-05-30T14:42:33.2450088+03:00",
      "translated_from": "enGB",
      "translation_date": "2023-05-30T14:42:33.2450091+03:00",
      "original_text": "\"Well, elantach. Since your will supersedes human laws on xenos, and I will face no reprisals while I am by your side — I accept your offer.\"",
      "traits": [
        {
          "trait": "Translated",
          "trait_date": "2023-05-30T14:42:33.2450103+03:00",
          "locale_text": "«De acuerdo, elantach. Ya que tu voluntad se antepone a las leyes humanas sobre los xenos y, por tanto, no sufriré represalias mientras esté a tu lado... acepto tu oferta»."
        }
      ]
    },
    {
      "locale": "jaJP",
      "text": "「さて、エランタ。あなたの意思が異種族に対する人間の法に優先するのならば、あなたの傍にいる間は報復行為に遭うこともないわけだ――その提案を受けよう」",
      "modification_date": "2023-07-12T13:08:53.2638316+03:00",
      "translated_from": "enGB",
      "translation_date": "2023-07-12T13:08:53.2638319+03:00",
      "original_text": "\"Well, elantach. Since your will supersedes human laws on xenos, and I will face no reprisals while I am by your side — I accept your offer.\"",
      "traits": [
        {
          "trait": "Translated",
          "trait_date": "2023-07-12T13:08:53.2638338+03:00",
          "locale_text": "「さて、エランタ。あなたの意思が異種族に対する人間の法に優先するのならば、あなたの傍にいる間は報復行為に遭うこともないわけだ――その提案を受けよう」"
        }
      ]
    },
    {
      "locale": "deDE",
      "text": "\"Nun, Elantach ... da Euer Wille mehr wiegt als die Menschengesetze für Xenos und ich an Eurer Seite keine Repressalien zu fürchten habe ... nehme ich Euer Angebot an.\"",
      "modification_date": "2023-08-01T11:37:43.6949544+03:00",
      "translated_from": "enGB",
      "translation_date": "2023-10-16T12:50:03.4256173+00:00",
      "original_text": "\"Well, elantach. Since your will supersedes human laws on xenos, and I will face no reprisals while I am by your side — I accept your offer.\"",
      "traits": [
        {
          "trait": "Translated",
          "trait_date": "2023-10-16T12:50:03.42562+00:00",
          "locale_text": "\"Nun, Elantach ... da Euer Wille mehr wiegt als die Menschengesetze für Xenos und ich an Eurer Seite keine Repressalien zu fürchten habe ... nehme ich Euer Angebot an.\""
        }
      ]
    },
    {
      "locale": "frFR",
      "text": "« Bien, elantach. Puisque votre volonté prime les lois humaines concernant les xénos et que je n'aurai pas à craindre de représailles à vos côtés, j'accepte votre offre. »",
      "modification_date": "2023-09-04T14:00:10.2118638+00:00",
      "translated_from": "enGB",
      "translation_date": "2023-11-26T20:19:50.8591374+00:00",
      "original_text": "\"Well, elantach. Since your will supersedes human laws on xenos, and I will face no reprisals while I am by your side — I accept your offer.\"",
      "traits": [
        {
          "trait": "Translated",
          "trait_date": "2023-11-26T20:19:50.8591387+00:00",
          "locale_text": "« Bien, elantach. Puisque votre volonté prime les lois humaines concernant les xénos et que je n'aurai pas à craindre de représailles à vos côtés, j'accepte votre offre. »"
        }
      ]
    },
    {
      "locale": "trTR",
      "text": "\"Pekâlâ elantach. Madem zenolara yönelik kanunlarımızı geçersiz kılacak bir iradeye sahipsin ve yanındayken misillemeden korkmam gerekmeyecek, o hâlde teklifini kabul ediyorum.\"",
      "modification_date": "2024-02-13T12:16:47.161995+00:00",
      "translated_from": "enGB",
      "translation_date": "2024-02-13T12:16:47.1619959+00:00",
      "original_text": "\"Well, elantach. Since your will supersedes human laws on xenos, and I will face no reprisals while I am by your side — I accept your offer.\"",
      "traits": [
        {
          "trait": "Translated",
          "trait_date": "2024-02-13T12:16:47.1619973+00:00",
          "locale_text": "\"Pekâlâ elantach. Madem zenolara yönelik kanunlarımızı geçersiz kılacak bir iradeye sahipsin ve yanındayken misillemeden korkmam gerekmeyecek, o hâlde teklifini kabul ediyorum.\""
        }
      ]
    },
    {
      "locale": "dev",
      "text": "",
      "modification_date": "2024-04-17T17:23:21.2713772+00:00",
      "translation_comment": "Компаньон попадает в ростер",
      "traits": []
    }
  ],
  "string_traits": [
    {
      "trait": "левшеяп",
      "trait_date": "2024-11-19T08:31:58.4840132+00:00",
      "locale_text": ""
    }
  ]
}